{
  "version": 1,
  "license": "CC-BY-SA-3.0",
  "copyright": "Taken from VoreStation13 commits: https://github.com/VOREStation/VOREStation/commit/4ceb5ff6a90fabd885b452a78e365a4cdd6aa94d, https://github.com/VOREStation/VOREStation/commit/63f1700bdae6ef38c8ce880da29d9518cc920884, https://github.com/VOREStation/VOREStation/commit/4315c04a0ea01ed8cfe974b37615c37def791804, https://github.com/VOREStation/VOREStation/commit/5e7540c4ae79e7d255dc477f911ec067408986db",
  "size": {
    "x": 32,
    "y": 32
  },
  "states": [
      {
          "name": "bra",
          "directions": 4
      },
      {
          "name": "bra_neko",
          "directions": 4
      },
      {
          "name": "lacy_bra",
          "directions": 4
      },
      {
          "name": "lacy_bra_alt",
          "directions": 4
      },
      {
          "name": "lacy_bra_alt_stripe",
          "directions": 4
      },
      {
          "name": "sports_bra",
          "directions": 4
      },
      {
          "name": "sports_bra_alt",
          "directions": 4
      },
      {
          "name": "striped_bra",
          "directions": 4
      },
      {
          "name": "halterneck_bra",
          "directions": 4
      }
  ]
}
